{
  "name": "Moonlight Island Sky Edition",
  "version": "4.2.0",
  "description": "Moon glow + sky palette only (no deep ocean tones) + fixed toolbar.",
  "authors": [
    {
      "name": "@Rxdransh",
      "id": "908089062294949888"
    }
  ],

  "semanticColors": {
    "ANDROID_RIPPLE": ["#79D8FF33"],
    "TEXT_NORMAL": ["#F2FBFF"],
    "TEXT_MUTED": ["#7EA3C0"],
    "TEXT_DANGER": ["#79D8FF"],
    "TEXT_LINK": ["#79D8FF"],

    "HEADER_PRIMARY": ["#F2FBFF"],
    "HEADER_SECONDARY": ["#CFF1FF"],
    "HEADER_MUTED": ["#7EA3C0"],

    "TOOLBAR_BACKGROUND": ["#0C1F3A"],
    "TITLEBAR_BACKGROUND": ["#0C1F3A"],
    "STATUSBAR": ["#0C1F3A"],
    "NAVIGATION_BAR_BACKGROUND": ["#0C1F3A"],
    "NAVIGATION_BAR_ICON_ACTIVE": ["#79D8FF"],
    "NAVIGATION_BAR_ICON_DEFAULT": ["#7EA3C0"],

    "INPUT_BACKGROUND": ["#183A63"],
    "SEARCH_BAR_BACKGROUND": ["#183A63"],
    "SEARCH_BAR_BACKGROUND_FOCUSED": ["#1F4A78"],

    "PROFILE_GRADIENT_PRIMARY": ["#79D8FF"],
    "PROFILE_GRADIENT_SECONDARY": ["#CFF1FF"],

    "SCROLLBAR_THIN_THUMB": ["#79D8FF4D"],
    "SCROLLBAR_THIN_TRACK": ["#0C1F3A"],

    "BG_BACKDROP": ["#0C1F3A80"],
    "BACKGROUND_PRIMARY": ["#0C1F3A"],
    "BACKGROUND_SECONDARY": ["#122C4D"],
    "BACKGROUND_SECONDARY_ALT": ["#183A63"],
    "BACKGROUND_TERTIARY": ["#0A1A31"],
    "BACKGROUND_ACCENT": ["#79D8FF"],
    "BACKGROUND_FLOATING": ["#122C4D"],
    "BACKGROUND_MOBILE_PRIMARY": ["#0C1F3A"],
    "BACKGROUND_MOBILE_SECONDARY": ["#122C4D"],
    "BACKGROUND_NESTED_FLOATING": ["#122C4D"],

    "BACKGROUND_MESSAGE_HOVER": ["#79D8FF1A"],
    "BACKGROUND_MODIFIER_HOVER": ["#79D8FF1A"],
    "BACKGROUND_MODIFIER_SELECTED": ["#79D8FF4D"],
    "BACKGROUND_MODIFIER_ACCENT": ["#79D8FF"],

    "INTERACTIVE_NORMAL": ["#CFF1FF"],
    "INTERACTIVE_HOVER": ["#FFFFFF"],
    "INTERACTIVE_ACTIVE": ["#FFFFFF"],
    "INTERACTIVE_MUTED": ["#406A8F"],

    "CHANNELTEXTAREA_BACKGROUND": ["#0A1A31"],
    "CHANNEL_ICON": ["#7EA3C0"],
    "CHANNELS_DEFAULT": ["#7EA3C0"],

    "CHAT_BACKGROUND": ["#081426"],
    "SPOILER_HIDDEN_BACKGROUND": ["#183A63"],
    "KEYBOARD": ["#0C1F3A"],

    "ACTIVITY_CARD_BACKGROUND": ["#122C4D"],
    "REDESIGN_ACTIVITY_CARD_BACKGROUND": ["#183A63"],
    "REDESIGN_ACTIVITY_CARD_BORDER": ["#79D8FF"],

    "BG_MOD_FAINT": ["#183A63"],
    "BG_MOD_SUBTLE": ["#79D8FF1A"],
    "BG_MOD_STRONG": ["#79D8FF4D"],

    "CARD_PRIMARY_BG": ["#0C1F3A"],
    "CARD_PRIMARY_PRESSED_BG": ["#183A63"],
    "CARD_SECONDARY_BG": ["#183A63"],
    "CARD_SECONDARY_PRESSED_BG": ["#122C4D"],

    "REDESIGN_BUTTON_SECONDARY_BACKGROUND": ["#183A63"],
    "REDESIGN_BUTTON_SECONDARY_PRESSED_BACKGROUND": ["#122C4D"],
    "REDESIGN_BUTTON_SECONDARY_ALT_BACKGROUND": ["#183A63"],
    "REDESIGN_BUTTON_SECONDARY_BORDER": ["#79D8FF"],

    "BORDER_FAINT": ["#79D8FF1A"],
    "BORDER_STRONG": ["#79D8FF"],
    "BORDER_SUBTLE": ["#79D8FF33"]
  },

  "background": {
    "blur": 0.6,
    "url": "https://files.catbox.moe/g4awcz.jpg",
    "alpha": 0.55
  },

  "spec": 2
}